autobright/__init__.py
autobright/__main__.py
autobright/colorhugals.py
autobright/core.py
autobright/ddccontrol.py
autobright/measurements.py
autobright/models.py
autobright/webui.py
autobright-0.1.0.dist-info/entry_points.txt
autobright-0.1.0.dist-info/WHEEL
autobright-0.1.0.dist-info/METADATA
autobright-0.1.0.dist-info/RECORD
