Metadata-Version: 2.1
Name: autobright
Version: 0.1.0
Summary: Automatically adjust display brightness with external sensor
License: MIT
Author: Martin Ueding
Author-email: mu@martin-ueding.de
Requires-Python: >=3.8,<4.0
Classifier: License :: OSI Approved :: MIT License
Classifier: Programming Language :: Python :: 3
Classifier: Programming Language :: Python :: 3.8
Classifier: Programming Language :: Python :: 3.9
Requires-Dist: altair (>=4.1.0,<5.0.0)
Requires-Dist: appdirs (>=1.4.4,<2.0.0)
Requires-Dist: pandas (>=1.3.4,<2.0.0)
Requires-Dist: streamlit (>=1.2.0,<2.0.0)
